bdci/__init__.py
bdci/bdrate_old.py
bdci/calculator.py
bdci/estimators.py
bdci/functional.py
bdci/utils.py
bdci/neuralbd/__init__.py
bdci/neuralbd/data.py
bdci/neuralbd/mlp_with_trainer.py
bdci/neuralbd/neural_estimator.py
bdci/neuralbd/segments.py
bdci/neuralbd/train_neuralbd.py
bdci/neuralbd/train_utils.py
bdci/neuralbd/types.py
bdci-1.0.0.dist-info/METADATA
bdci-1.0.0.dist-info/WHEEL
bdci-1.0.0.dist-info/top_level.txt
bdci-1.0.0.dist-info/RECORD
