Metadata-Version: 2.1
Name: bdci
Version: 1.0.0
Summary: Bjontegaard Delta Confidence Interval
Home-page: https://github.com/fgvfgfg564/BDCI
Author: fgvfgfg564
Author-email: xyhang@pku.edu.cn
License: MIT Licence
Keywords: pip,bdci,vqi
Platform: any
Requires-Dist: numpy
Requires-Dist: scipy
Requires-Dist: torch >=2.0.1
Requires-Dist: tqdm
Requires-Dist: transformers
Requires-Dist: typing-extensions
